helpers/bin2bcd.v
`timescale 1ns/1ns

module bin2bcd(input [5:0]valoare_bin, output [3:0]BCD0, BCD1);
	
	integer i;
	reg [7:0]bcd;

	always @(posedge valoare_bin)
	 begin

		bcd = 0;	//initiez bcd la 0
		for(i = 0; i < 6; i++)	//8 iteratii
		begin
			bcd = {bcd[6:0], valoare_bin[5-i]};	//concatenare
			//daca un digit din bcd e > 4, adun 3 la el
			if(i < 5 && bcd[3:0] > 4)
				bcd[3:0] = bcd[3:0] + 3;
			if(i < 5 && bcd[7:4] > 4)
				bcd[7:4] = bcd[7:4] + 3;
		end
	end
	
	assign BCD0 = bcd[7:4];
	assign BCD1 = bcd[3:0];



endmodule

helpers/test_b2b.v
`timescale 1ns/1ns

module test_b2b();
	
	reg [5:0] valoare_bin;
	wire [3:0] BCD0;
	wire [3:0] BCD1;
	bin2bcd b(valoare_bin, BCD0, BCD1);

	initial begin 
	$dumpfile("b2b.vcd");
	$dumpvars;

	valoare_bin=0;

	forever #5 valoare_bin=~valoare_bin;

	end

	initial begin
	#60;

	$finish;

	end
endmodule

lucrare1/numarator.vcd
$date
	Fri Mar 20 17:25:08 2020
$end
$version
	Icarus Verilog
$end
$timescale
	1ns
$end
$scope module test_b2b $end
$var wire 4 ! BCD1 [3:0] $end
$var wire 4 " BCD0 [3:0] $end
$var reg 6 # valoare_bin [5:0] $end
$scope module b $end
$var wire 6 $ valoare_bin [5:0] $end
$var wire 4 % BCD1 [3:0] $end
$var wire 4 & BCD0 [3:0] $end
$var reg 8 ' bcd [7:0] $end
$var integer 32 ( i [31:0] $end
$upscope $end
$upscope $end
$enddefinitions $end
#0
$dumpvars
b110 (
b0 '
b0 &
b0 %
b0 $
b0 #
b0 "
b0 !
$end
#5
b110 "
b110 &
b11 !
b11 %
b1100011 '
b110 (
b111111 #
b111111 $
#10
b0 "
b0 &
b0 !
b0 %
b110 (
b0 '
b0 #
b0 $
#15
b110 "
b110 &
b11 !
b11 %
b1100011 '
b110 (
b111111 #
b111111 $
#20
b0 "
b0 &
b0 !
b0 %
b110 (
b0 '
b0 #
b0 $
#25
b110 "
b110 &
b11 !
b11 %
b1100011 '
b110 (
b111111 #
b111111 $
#30
b0 "
b0 &
b0 !
b0 %
b110 (
b0 '
b0 #
b0 $
#35
b110 "
b110 &
b11 !
b11 %
b1100011 '
b110 (
b111111 #
b111111 $
#40
b0 "
b0 &
b0 !
b0 %
b110 (
b0 '
b0 #
b0 $
#45
b110 "
b110 &
b11 !
b11 %
b1100011 '
b110 (
b111111 #
b111111 $
#50
b0 "
b0 &
b0 !
b0 %
b110 (
b0 '
b0 #
b0 $
#55
b110 "
b110 &
b11 !
b11 %
b1100011 '
b110 (
b111111 #
b111111 $
#60
b0 "
b0 &
b0 !
b0 %
b110 (
b0 '
b0 #
b0 $
